mocherry/__init__.py
mocherry/settings.py
mocherry/contrib/__init__.py
mocherry/contrib/thirdparty/__init__.py
mocherry/contrib/thirdparty/mailchimp/__init__.py
mocherry/contrib/thirdparty/mailchimp/mailchimp.py
mocherry/library/__init__.py
mocherry/library/commands.py
mocherry/library/databases.py
mocherry/library/encryption.py
mocherry/library/helpers.py
mocherry/library/views.py
mocherry/library/wsgi.py
mocherry/library/cli/__init__.py
mocherry/library/cli/commands.py
mocherry/library/http/__init__.py
mocherry/library/http/status.py
mocherry-1.2.dist-info/LICENSE
mocherry-1.2.dist-info/METADATA
mocherry-1.2.dist-info/WHEEL
mocherry-1.2.dist-info/entry_points.txt
mocherry-1.2.dist-info/top_level.txt
mocherry-1.2.dist-info/zip-safe
mocherry-1.2.dist-info/RECORD
