Metadata-Version: 2.1
Name: mocherry
Version: 1.2
Summary: CherryPy REST webservice framework with MongoDB ORM support
Home-page: https://github.com/techunits/mocherry
Author: Sougata P.
Author-email: skall.paul@gmail.com
License: UNKNOWN
Download-URL: https://github.com/techunits/mocherry/archive/1.2.tar.gz
Platform: UNKNOWN
Classifier: Programming Language :: Python
Classifier: Programming Language :: Python :: 3
Classifier: Programming Language :: Python :: 3 :: Only
Classifier: Programming Language :: Python :: 3.6
Classifier: Programming Language :: Python :: 3.7
Classifier: Programming Language :: Python :: 3.8
Classifier: License :: OSI Approved :: MIT License
Classifier: Operating System :: OS Independent
Classifier: Intended Audience :: Developers
Classifier: Environment :: Web Environment
Classifier: Topic :: Internet :: WWW/HTTP
Classifier: Topic :: Internet :: WWW/HTTP :: Dynamic Content
Classifier: Topic :: Internet :: WWW/HTTP :: WSGI
Classifier: Topic :: Software Development :: Libraries :: Application Frameworks
Classifier: Topic :: Software Development :: Libraries :: Python Modules
Requires-Python: >=3.6
Requires-Dist: celery
Requires-Dist: cherrypy-cors
Requires-Dist: faker
Requires-Dist: mongoengine
Requires-Dist: requests
Requires-Dist: routes
